clipsync/__init__.py
clipsync/api.py
clipsync/auth.py
clipsync/cli.py
clipsync/monitor.py
xconnect-1.0.2.dist-info/METADATA
xconnect-1.0.2.dist-info/WHEEL
xconnect-1.0.2.dist-info/entry_points.txt
xconnect-1.0.2.dist-info/top_level.txt
xconnect-1.0.2.dist-info/RECORD
