Metadata-Version: 2.4
Name: xconnect
Version: 1.0.2
Summary: A professional cross-platform clipboard synchronization CLI by XDT Labs.
Author-email: XDT Labs <contact@xdtlabs.com>
License: MIT
Project-URL: Homepage, https://github.com/xdtlabs/csync
Project-URL: Bug Tracker, https://github.com/xdtlabs/csync/issues
Keywords: clipboard,sync,cross-platform,cli,firebase
Classifier: Development Status :: 4 - Beta
Classifier: Environment :: Console
Classifier: Intended Audience :: Developers
Classifier: License :: OSI Approved :: MIT License
Classifier: Operating System :: OS Independent
Classifier: Programming Language :: Python :: 3
Classifier: Programming Language :: Python :: 3.8
Classifier: Programming Language :: Python :: 3.9
Classifier: Programming Language :: Python :: 3.10
Classifier: Programming Language :: Python :: 3.11
Classifier: Programming Language :: Python :: 3.12
Classifier: Topic :: Utilities
Requires-Python: >=3.8
Requires-Dist: pyperclip
Requires-Dist: firebase-admin
Requires-Dist: click
Requires-Dist: requests
Requires-Dist: rich
Requires-Dist: flask
Requires-Dist: pyfiglet
